src/__init__.py
src/conftest.py
src/pytest.ini
src/pytest_plugin.py
src/Configuration/__init__.py
src/Configuration/config.ini
src/Logs/.gitkeep
src/Logs/__init__.py
src/Reports/.gitkeep
src/Reports/__init__.py
src/Screenshots/.gitkeep
src/Screenshots/__init__.py
src/TestData/__init__.py
src/TestData/data_generator.py
src/Utilities/__init__.py
src/Utilities/email_handler.py
src/Utilities/log_handler.py
src/Utilities/read_properties.py
src/Utilities/screenshot.py
src/Utilities/test_base.py
src/Utilities/web_driver_helper.py
ui_demo_framework-1.4.7.dist-info/METADATA
ui_demo_framework-1.4.7.dist-info/WHEEL
ui_demo_framework-1.4.7.dist-info/entry_points.txt
ui_demo_framework-1.4.7.dist-info/top_level.txt
ui_demo_framework-1.4.7.dist-info/RECORD
