Metadata-Version: 2.1
Name: ui_demo_framework
Version: 1.4.7
Summary: A UI Testing Framework
Home-page: https://github.com/mrinal2323/UI_Demo_Framework
Author: Mrinal Gautam
Author-email: mrinalsinghgautam@gmail.com
Classifier: Programming Language :: Python :: 3
Classifier: License :: OSI Approved :: MIT License
Classifier: Operating System :: OS Independent
Requires-Python: >=3.7
Requires-Dist: pytest
Requires-Dist: selenium
Requires-Dist: requests
Requires-Dist: pytest-html
Requires-Dist: pytest-xdist
Requires-Dist: openpyxl
Requires-Dist: jsonschema
Requires-Dist: flake8
Requires-Dist: pyjwt
Requires-Dist: urllib3
Requires-Dist: jwt
Requires-Dist: pytest-bdd
Requires-Dist: webdriver-manager
Requires-Dist: names
Requires-Dist: faker
Requires-Dist: polling2
Requires-Dist: pytest-repeat
Requires-Dist: imapclient
Requires-Dist: mail-parser
Requires-Dist: pandas
Requires-Dist: psutil
Requires-Dist: wheel
Requires-Dist: twine
